MANIFEST.in
README.rst
setup.py
sentinela/__init__.py
sentinela/sentinela.py
sentinela.egg-info/PKG-INFO
sentinela.egg-info/SOURCES.txt
sentinela.egg-info/dependency_links.txt
sentinela.egg-info/entry_points.txt
sentinela.egg-info/requires.txt
sentinela.egg-info/top_level.txt
sentinela/config/sentinela.cfg
sentinela/core/__init__.py
sentinela/core/base_action.py
sentinela/core/base_monitor.py
sentinela/core/sentinela.py
sentinela/core/tests/__init__.py
sentinela/core/tests/test_base_action.py
sentinela/core/tests/test_base_monitor.py
sentinela/core/tests/test_sentinela.py
sentinela/core/utils/__init__.py
sentinela/core/utils/log_handler.py
sentinela/core/utils/operating_system.py
sentinela/core/utils/rule_handler.py
sentinela/core/utils/tests/__init__.py
sentinela/core/utils/tests/test_rule_handler.py
sentinela/modules/__init__.py
sentinela/modules/actions/__init__.py
sentinela/modules/actions/debug_print.py
sentinela/modules/actions/shutdown.py
sentinela/modules/monitors/__init__.py
sentinela/modules/monitors/disk_usage.py
sentinela/modules/monitors/new_log_entries.py
sentinela/rules/__init__.py
sentinela/rules/apache_debug.py
sentinela/rules/apache_shutdown.py
sentinela/tests/__init__.py
sentinela/tests/test_sentinela.py